{
  "id": "/questions/questions/2838518.json",
  "creationDate": "2010-05-15T01:19:54.967",
  "body": "\n\nIf I have a selector like \n\n\t$.('.active');\n\t\n\nHow can I see how many items that matched?\n\nAlternatively, is there an easy way to see if more than zero elements were matched?",
  "lastActivityDate": "2010-05-15T01:26:17.433",
  "title": "jQuery: See how many elements a selector matched?",
  "tags": [
    "javascript",
    "jquery",
    "jquery-selectors"
  ],
  "docScore": 0,
  "comments": [],
  "answers": [],
  "creationYearMonth": "201005",
  "itemTally": 0,
  "owner": null
}